odoo8_addon_crm_construction_calculator-8.0.0.1.0-py2.7-nspkg.pth
odoo8_addon_crm_construction_calculator-8.0.0.1.0.dist-info/top_level.txt
odoo8_addon_crm_construction_calculator-8.0.0.1.0.dist-info/WHEEL
odoo8_addon_crm_construction_calculator-8.0.0.1.0.dist-info/RECORD
odoo8_addon_crm_construction_calculator-8.0.0.1.0.dist-info/metadata.json
odoo8_addon_crm_construction_calculator-8.0.0.1.0.dist-info/DESCRIPTION.rst
odoo8_addon_crm_construction_calculator-8.0.0.1.0.dist-info/METADATA
odoo8_addon_crm_construction_calculator-8.0.0.1.0.dist-info/namespace_packages.txt
odoo_addons/crm_construction_calculator/demo.xml
odoo_addons/crm_construction_calculator/views.xml
odoo_addons/crm_construction_calculator/models.py
odoo_addons/crm_construction_calculator/__openerp__.py
odoo_addons/crm_construction_calculator/__init__.py
odoo_addons/crm_construction_calculator/README.rst
odoo_addons/crm_construction_calculator/i18n/crm_construction_calculator.po
odoo_addons/crm_construction_calculator/i18n/nl_BE.po
odoo_addons/crm_construction_calculator/static/description/example-opportunity-treeview.png
odoo_addons/crm_construction_calculator/static/description/example-opportunity.png
odoo_addons/crm_construction_calculator/static/description/index.html
odoo_addons/crm_construction_calculator/static/description/example-calculator-planning.png
odoo_addons/crm_construction_calculator/static/description/icon.png
